zlado
