Metadata-Version: 2.1
Name: zlado
Version: 3.0.6
Summary: ado 显示 ecs列表
Home-page: http://www.baidu.com
Author: 桃园路后上天桥
Author-email: shimuly@qq.com
License: MIT
Platform: UNKNOWN
Requires-Python: >=3.0
